odoo/addons/l10n_es_pos_sii/README.rst
odoo/addons/l10n_es_pos_sii/__init__.py
odoo/addons/l10n_es_pos_sii/__manifest__.py
odoo/addons/l10n_es_pos_sii/data/ir_cron.xml
odoo/addons/l10n_es_pos_sii/i18n/es.po
odoo/addons/l10n_es_pos_sii/i18n/l10n_es_pos_sii.pot
odoo/addons/l10n_es_pos_sii/models/__init__.py
odoo/addons/l10n_es_pos_sii/models/pos_order.py
odoo/addons/l10n_es_pos_sii/models/pos_session.py
odoo/addons/l10n_es_pos_sii/models/res_company.py
odoo/addons/l10n_es_pos_sii/readme/CONFIGURE.md
odoo/addons/l10n_es_pos_sii/readme/CONTRIBUTORS.md
odoo/addons/l10n_es_pos_sii/readme/DESCRIPTION.md
odoo/addons/l10n_es_pos_sii/readme/ROADMAP.md
odoo/addons/l10n_es_pos_sii/static/description/icon.png
odoo/addons/l10n_es_pos_sii/static/description/index.html
odoo/addons/l10n_es_pos_sii/static/src/app/screens/ticket_screen/invoice_button.esm.js
odoo/addons/l10n_es_pos_sii/tests/__init__.py
odoo/addons/l10n_es_pos_sii/tests/test_l10n_es_pos_sii.py
odoo/addons/l10n_es_pos_sii/tests/json/sii_pos_order_iva10b.json
odoo/addons/l10n_es_pos_sii/tests/json/sii_pos_order_iva21b.json
odoo/addons/l10n_es_pos_sii/tests/json/sii_pos_order_iva21b_iva10b.json
odoo/addons/l10n_es_pos_sii/tests/json/sii_pos_order_refund_iva21b.json
odoo/addons/l10n_es_pos_sii/views/pos_order.xml
odoo/addons/l10n_es_pos_sii/views/res_company.xml
odoo_addon_l10n_es_pos_sii-18.0.1.0.0.2.dist-info/METADATA
odoo_addon_l10n_es_pos_sii-18.0.1.0.0.2.dist-info/WHEEL
odoo_addon_l10n_es_pos_sii-18.0.1.0.0.2.dist-info/top_level.txt
odoo_addon_l10n_es_pos_sii-18.0.1.0.0.2.dist-info/RECORD
